marine_omics-0.1.20.dist-info/licenses/LICENSE
momics/__init__.py
momics/constants.py
momics/diversity.py
momics/metadata.py
momics/networks.py
momics/panel_utils.py
momics/plotting.py
momics/stats.py
momics/taxonomy.py
momics/utils.py
momics/galaxy/__init__.py
momics/galaxy/bio_blend.py
momics/galaxy/gecco.py
momics/loader/__init__.py
momics/loader/parquets.py
momics/loader/ro_crates.py
momics/loader/utils.py
momics/test/__init__.py
momics/test/fixtures.py
momics/test/test_diversity.py
momics/test/test_galaxy.py
momics/test/test_loader.py
momics/test/test_networks.py
momics/test/test_panel_utils.py
momics/test/test_plotting.py
momics/test/test_taxonomy.py
momics/test/test_utils.py
marine_omics-0.1.20.dist-info/METADATA
marine_omics-0.1.20.dist-info/WHEEL
marine_omics-0.1.20.dist-info/top_level.txt
marine_omics-0.1.20.dist-info/RECORD
